server_analysis_report/__init__.py
server_analysis_report/__manifest__.py
server_analysis_report/models/__init__.py
server_analysis_report/models/disk_io.py
server_analysis_report/models/server_monitor.py
monitoring_systems-0.1.0.dist-info/METADATA
monitoring_systems-0.1.0.dist-info/WHEEL
monitoring_systems-0.1.0.dist-info/entry_points.txt
monitoring_systems-0.1.0.dist-info/top_level.txt
monitoring_systems-0.1.0.dist-info/RECORD
